Entrega4/Registers.v
module Registers(clock, reset, addra, dataa, addrb, datab, enc, addrc, datac);

//-------------------------------------inputs----------------------
	input		clock;
	input		reset;
	input	[4:0]	addra;
	input	[4:0]	addrb;
	input 		enc;
	input	[4:0]	addrc;
	input	[31:0]	datac;
	
//-----------------------------------outputs-----------------------

	output  [31:0]	dataa;
	output  [31:0]	datab;
	
//---------------------------------registers-----------------------

	reg  	[31:0]	dataa;
	reg  	[31:0]	ass_dataa // entrega 5
	reg  	[31:0]	datab;
	reg  	[31:0]	ass_datab // entrega 5
	reg	[31:0]	registers [31:0];

//------------------------------auxiliares-------------------------


	parameter	number_of_registers = 32;
//-----------------------REGISTERS BANKS---------------------------


	
always @(posedge clock) begin

	dataa <= registers[addra];
	datab <= registers[addrb];
	
		

end

always @(posedge clock )begin

	if (enc == 1'b1)begin

		registers [addrc] <= datac;

	end

end

// entrega 5
always @(addra) begin 
	
	registers [ass_dataa] <= registers [dataa];
	
end

// entrega 5
always @(addrb) begin

	registers [ass_datab] <= registers [datab];
	
end

genvar counter;
generate

 
	for (counter = 0; counter < number_of_registers ; counter = counter + 1)begin: RST
	
		always @(negedge clock  &&  reset) begin
		
			registers [counter] <= 32'b0;

		end

	end

endgenerate
endmodule

Entrega5/src/Registers_tb.v
module Registers_tb(); 
	//--------------Entradas-----------------
    reg clock;
    reg reset;
    reg enc;
    reg [4:0] addra;
    reg [4:0] addrb;
    reg [4:0] addrc;
    reg [31:0] datac;
    //-------------------------------------
    
    //------------Saídas-------------------
    wire [31:0] dataa;
    wire [31:0] ass_dataa;
    wire [31:0] datab;
    wire [31:0] ass_datab;
    
    //-------------------------------------
    
    //------------------------------------
    Registers dut(clock,
		  reset,
		  addra,
		  dataa,
		  ass_dataa,
		  addrb,
		  datab,
		  ass_datab,
		  enc,
		  addrc,
		  datac);
	parameter delay=10;
	integer i;
	//-------------------------------------
  
	initial begin
		$dumpfile ("Registers.vcd");
		$dumpvars;
		clock=0;
		
		//Testando se o Reset funciona
		reset=1;
		#delay;
		$display("Teste do Reset\n");
		for(i=0; i<32; i=i+1)begin
			addra=i;
			addrb=i;
			$display("Registrador Ass A: %b\nRegistrador Ass B: %b\nEndereço: %d\n",ass_dataa,ass_datab,i);
			$display("Registrador A: %b\nRegistrador B: %b\nEndereço: %d\n",dataa,datab,i);
			#delay;
			
			//Subindo o clock
			clock=~clock;
			
			#delay;
			//Descendo o clock para entrar no for novamente
			clock=~clock;
			
			$display("\n\nRegistrador A: %b\nRegistrador B: %b\nEndereço: %d\n",dataa,datab,);
			$display("Registrador Ass A: %b\nRegistrador Ass B: %b\nEndereço: %d\n",ass_dataa,ass_datab);
		end
		
		reset=0;
		
		//Testando se escreve com enc=0
		enc=0;
		#delay;
		$display("Teste se escreve com enc=0\n");
		for(i=0; i<32; i=i+1)begin
			addrc=i;
			addra=i;
			datac=$random;
			#delay;
			
			//Subindo o clock
			clock=~clock;
			
			#delay;
			//Descendo o clock para entrar no for novamente
			clock=~clock;
			
			$display("Foi pedido para escrever: %d no enrereço: %d e o que tem e: %d\n",datac,i,dataa);
		end
		
		//Testando se escreve com enc=1
		enc=1;
		#delay;
		$display("Teste se escreve com enc=1\n");
		for(i=0; i<32; i=i+1)begin
			addrc=i;
			#delay;
			datac=$random;
			#delay;
			$display("Registrador Ass A: %b\nRegistrador Ass B: %b\nEndereço: %d\n",ass_dataa,ass_datab);
			//Subindo o clock
			clock=~clock;
			#delay;
			//Descendo o clock para entrar no for novamente
			clock=~clock;
			
			addra=i;
			//Subindo o clock
			clock=~clock;
			#delay;
			//Descendo o clock para entrar no for novamente
			clock=~clock;
			$display("Foi pedido para escrever: %d no enrereço: %d e o que tem e: %d\n",datac,i,dataa);
		end
		$finish;
    end
endmodule

Entrevista3/src/Registers.vcd
$date
	Wed Jun  4 21:34:35 2014
$end
$version
	Icarus Verilog
$end
$timescale
	1s
$end
$scope module Registers_tb $end
$var wire 32 ! ass_dataa [31:0] $end
$var wire 32 " ass_datab [31:0] $end
$var wire 32 # dataa [31:0] $end
$var wire 32 $ datab [31:0] $end
$var reg 5 % addra [4:0] $end
$var reg 5 & addrb [4:0] $end
$var reg 5 ' addrc [4:0] $end
$var reg 1 ( clock $end
$var reg 32 ) datac [31:0] $end
$var reg 1 * enc $end
$var integer 32 + i [31:0] $end
$var reg 1 , reset $end
$scope module dut $end
$var wire 5 - addra [4:0] $end
$var wire 5 . addrb [4:0] $end
$var wire 5 / addrc [4:0] $end
$var wire 1 0 clock $end
$var wire 32 1 datac [31:0] $end
$var wire 1 2 enc $end
$var wire 1 3 reset $end
$var reg 32 4 ass_dataa [31:0] $end
$var reg 32 5 ass_datab [31:0] $end
$var reg 32 6 dataa [31:0] $end
$var reg 32 7 datab [31:0] $end
$scope begin RST[0] $end
$upscope $end
$scope begin RST[1] $end
$upscope $end
$scope begin RST[2] $end
$upscope $end
$scope begin RST[3] $end
$upscope $end
$scope begin RST[4] $end
$upscope $end
$scope begin RST[5] $end
$upscope $end
$scope begin RST[6] $end
$upscope $end
$scope begin RST[7] $end
$upscope $end
$scope begin RST[8] $end
$upscope $end
$scope begin RST[9] $end
$upscope $end
$scope begin RST[10] $end
$upscope $end
$scope begin RST[11] $end
$upscope $end
$scope begin RST[12] $end
$upscope $end
$scope begin RST[13] $end
$upscope $end
$scope begin RST[14] $end
$upscope $end
$scope begin RST[15] $end
$upscope $end
$scope begin RST[16] $end
$upscope $end
$scope begin RST[17] $end
$upscope $end
$scope begin RST[18] $end
$upscope $end
$scope begin RST[19] $end
$upscope $end
$scope begin RST[20] $end
$upscope $end
$scope begin RST[21] $end
$upscope $end
$scope begin RST[22] $end
$upscope $end
$scope begin RST[23] $end
$upscope $end
$scope begin RST[24] $end
$upscope $end
$scope begin RST[25] $end
$upscope $end
$scope begin RST[26] $end
$upscope $end
$scope begin RST[27] $end
$upscope $end
$scope begin RST[28] $end
$upscope $end
$scope begin RST[29] $end
$upscope $end
$scope begin RST[30] $end
$upscope $end
$scope begin RST[31] $end
$upscope $end
$upscope $end
$upscope $end
$enddefinitions $end
#0
$dumpvars
bx 7
bx 6
bx 5
bx 4
13
x2
bx 1
00
bx /
b1 .
b1 -
1,
bx +
x*
bx )
0(
bx '
b1 &
b1 %
bx $
bx #
bx "
bx !
$end
#10
b0 5
b0 "
b0 4
b0 !
b0 &
b0 .
b0 %
b0 -
b0 +
#20
b0 7
b0 $
b0 6
b0 #
1(
10
#30
b1 &
b1 .
b1 %
b1 -
b1 +
0(
00
#40
1(
10
#50
b10 &
b10 .
b10 %
b10 -
b10 +
0(
00
#60
1(
10
#70
b11 &
b11 .
b11 %
b11 -
b11 +
0(
00
#80
1(
10
#90
b100 &
b100 .
b100 %
b100 -
b100 +
0(
00
#100
1(
10
#110
b101 &
b101 .
b101 %
b101 -
b101 +
0(
00
#120
1(
10
#130
b110 &
b110 .
b110 %
b110 -
b110 +
0(
00
#140
1(
10
#150
b111 &
b111 .
b111 %
b111 -
b111 +
0(
00
#160
1(
10
#170
b1000 &
b1000 .
b1000 %
b1000 -
b1000 +
0(
00
#180
1(
10
#190
b1001 &
b1001 .
b1001 %
b1001 -
b1001 +
0(
00
#200
1(
10
#210
b1010 &
b1010 .
b1010 %
b1010 -
b1010 +
0(
00
#220
1(
10
#230
b1011 &
b1011 .
b1011 %
b1011 -
b1011 +
0(
00
#240
1(
10
#250
b1100 &
b1100 .
b1100 %
b1100 -
b1100 +
0(
00
#260
1(
10
#270
b1101 &
b1101 .
b1101 %
b1101 -
b1101 +
0(
00
#280
1(
10
#290
b1110 &
b1110 .
b1110 %
b1110 -
b1110 +
0(
00
#300
1(
10
#310
b1111 &
b1111 .
b1111 %
b1111 -
b1111 +
0(
00
#320
1(
10
#330
b10000 &
b10000 .
b10000 %
b10000 -
b10000 +
0(
00
#340
1(
10
#350
b10001 &
b10001 .
b10001 %
b10001 -
b10001 +
0(
00
#360
1(
10
#370
b10010 &
b10010 .
b10010 %
b10010 -
b10010 +
0(
00
#380
1(
10
#390
b10011 &
b10011 .
b10011 %
b10011 -
b10011 +
0(
00
#400
1(
10
#410
b10100 &
b10100 .
b10100 %
b10100 -
b10100 +
0(
00
#420
1(
10
#430
b10101 &
b10101 .
b10101 %
b10101 -
b10101 +
0(
00
#440
1(
10
#450
b10110 &
b10110 .
b10110 %
b10110 -
b10110 +
0(
00
#460
1(
10
#470
b10111 &
b10111 .
b10111 %
b10111 -
b10111 +
0(
00
#480
1(
10
#490
b11000 &
b11000 .
b11000 %
b11000 -
b11000 +
0(
00
#500
1(
10
#510
b11001 &
b11001 .
b11001 %
b11001 -
b11001 +
0(
00
#520
1(
10
#530
b11010 &
b11010 .
b11010 %
b11010 -
b11010 +
0(
00
#540
1(
10
#550
b11011 &
b11011 .
b11011 %
b11011 -
b11011 +
0(
00
#560
1(
10
#570
b11100 &
b11100 .
b11100 %
b11100 -
b11100 +
0(
00
#580
1(
10
#590
b11101 &
b11101 .
b11101 %
b11101 -
b11101 +
0(
00
#600
1(
10
#610
b11110 &
b11110 .
b11110 %
b11110 -
b11110 +
0(
00
#620
1(
10
#630
b11111 &
b11111 .
b11111 %
b11111 -
b11111 +
0(
00
#640
1(
10
#650
0*
02
0,
03
b100000 +
0(
00
#660
b10010000101010011010100100100 )
b10010000101010011010100100100 1
b0 %
b0 -
b0 '
b0 /
b0 +
#670
1(
10
#680
b11000000100010010101111010000001 )
b11000000100010010101111010000001 1
b1 %
b1 -
b1 '
b1 /
b1 +
0(
00
#690
1(
10
#700
b10000100100001001101011000001001 )
b10000100100001001101011000001001 1
b10 %
b10 -
b10 '
b10 /
b10 +
0(
00
#710
1(
10
#720
b10110001111100000101011001100011 )
b10110001111100000101011001100011 1
b11 %
b11 -
b11 '
b11 /
b11 +
0(
00
#730
1(
10
#740
b110101110010111101100001101 )
b110101110010111101100001101 1
b100 %
b100 -
b100 '
b100 /
b100 +
0(
00
#750
1(
10
#760
b1000110110111111001100110001101 )
b1000110110111111001100110001101 1
b101 %
b101 -
b101 '
b101 /
b101 +
0(
00
#770
1(
10
#780
b10110010110000101000010001100101 )
b10110010110000101000010001100101 1
b110 %
b110 -
b110 '
b110 /
b110 +
0(
00
#790
1(
10
#800
b10001001001101110101001000010010 )
b10001001001101110101001000010010 1
b111 %
b111 -
b111 '
b111 /
b111 +
0(
00
#810
1(
10
#820
b111100111110001100000001 )
b111100111110001100000001 1
b1000 %
b1000 -
b1000 '
b1000 /
b1000 +
0(
00
#830
1(
10
#840
b110110101111100110100001101 )
b110110101111100110100001101 1
b1001 %
b1001 -
b1001 '
b1001 /
b1001 +
0(
00
#850
1(
10
#860
b111011001000111111000101110110 )
b111011001000111111000101110110 1
b1010 %
b1010 -
b1010 '
b1010 /
b1010 +
0(
00
#870
1(
10
#880
b11110100011011100110100111101 )
b11110100011011100110100111101 1
b1011 %
b1011 -
b1011 '
b1011 /
b1011 +
0(
00
#890
1(
10
#900
b1110110110101000101011111101101 )
b1110110110101000101011111101101 1
b1100 %
b1100 -
b1100 '
b1100 /
b1100 +
0(
00
#910
1(
10
#920
b1000110001011011111011110001100 )
b1000110001011011111011110001100 1
b1101 %
b1101 -
b1101 '
b1101 /
b1101 +
0(
00
#930
1(
10
#940
b1111100111111011110100111111001 )
b1111100111111011110100111111001 1
b1110 %
b1110 -
b1110 '
b1110 /
b1110 +
0(
00
#950
1(
10
#960
b11100011001101110010010011000110 )
b11100011001101110010010011000110 1
b1111 %
b1111 -
b1111 '
b1111 /
b1111 +
0(
00
#970
1(
10
#980
b11100010111101111000010011000101 )
b11100010111101111000010011000101 1
b10000 %
b10000 -
b10000 '
b10000 /
b10000 +
0(
00
#990
1(
10
#1000
b11010101000100111101001010101010 )
b11010101000100111101001010101010 1
b10001 %
b10001 -
b10001 '
b10001 /
b10001 +
0(
00
#1010
1(
10
#1020
b1110010101011111111011111100101 )
b1110010101011111111011111100101 1
b10010 %
b10010 -
b10010 '
b10010 /
b10010 +
0(
00
#1030
1(
10
#1040
b10111011110100100111001001110111 )
b10111011110100100111001001110111 1
b10011 %
b10011 -
b10011 '
b10011 /
b10011 +
0(
00
#1050
1(
10
#1060
b10001001001100101101011000010010 )
b10001001001100101101011000010010 1
b10100 %
b10100 -
b10100 '
b10100 /
b10100 +
0(
00
#1070
1(
10
#1080
b1000111111011001101101110001111 )
b1000111111011001101101110001111 1
b10101 %
b10101 -
b10101 '
b10101 /
b10101 +
0(
00
#1090
1(
10
#1100
b1111001001100000110100111110010 )
b1111001001100000110100111110010 1
b10110 %
b10110 -
b10110 '
b10110 /
b10110 +
0(
00
#1110
1(
10
#1120
b11100111011101101001011011001110 )
b11100111011101101001011011001110 1
b10111 %
b10111 -
b10111 '
b10111 /
b10111 +
0(
00
#1130
1(
10
#1140
b11110100000000000111101011101000 )
b11110100000000000111101011101000 1
b11000 %
b11000 -
b11000 '
b11000 /
b11000 +
0(
00
#1150
1(
10
#1160
b11100010110010100100111011000101 )
b11100010110010100100111011000101 1
b11001 %
b11001 -
b11001 '
b11001 /
b11001 +
0(
00
#1170
1(
10
#1180
b101110010110000100100101011100 )
b101110010110000100100101011100 1
b11010 %
b11010 -
b11010 '
b11010 /
b11010 +
0(
00
#1190
1(
10
#1200
b11011110100011100010100010111101 )
b11011110100011100010100010111101 1
b11011 %
b11011 -
b11011 '
b11011 /
b11011 +
0(
00
#1210
1(
10
#1220
b10010110101010110101100000101101 )
b10010110101010110101100000101101 1
b11100 %
b11100 -
b11100 '
b11100 /
b11100 +
0(
00
#1230
1(
10
#1240
b10110010101001110010011001100101 )
b10110010101001110010011001100101 1
b11101 %
b11101 -
b11101 '
b11101 /
b11101 +
0(
00
#1250
1(
10
#1260
b10110001111011110110001001100011 )
b10110001111011110110001001100011 1
b11110 %
b11110 -
b11110 '
b11110 /
b11110 +
0(
00
#1270
1(
10
#1280
b101011100111000011100001010 )
b101011100111000011100001010 1
b11111 %
b11111 -
b11111 '
b11111 /
b11111 +
0(
00
#1290
1(
10
#1300
1*
12
b100000 +
0(
00
#1310
b0 '
b0 /
b0 +
#1320
b11000000001110110010001010000000 )
b11000000001110110010001010000000 1
#1330
1(
10
#1340
b11000000001110110010001010000000 6
b11000000001110110010001010000000 #
b11000000001110110010001010000000 4
b11000000001110110010001010000000 !
b0 %
b0 -
1(
10
#1350
b1 '
b1 /
b1 +
0(
00
#1360
b10000011001000010000100100000 )
b10000011001000010000100100000 1
#1370
1(
10
#1380
b10000011001000010000100100000 6
b10000011001000010000100100000 #
b10000011001000010000100100000 4
b10000011001000010000100100000 !
b1 %
b1 -
1(
10
#1390
b10 '
b10 /
b10 +
0(
00
#1400
b1010101011110000100010110101010 )
b1010101011110000100010110101010 1
#1410
1(
10
#1420
b1010101011110000100010110101010 6
b1010101011110000100010110101010 #
b1010101011110000100010110101010 4
b1010101011110000100010110101010 !
b10 %
b10 -
1(
10
#1430
b11 '
b11 /
b11 +
0(
00
#1440
b11001110110011001100110010011101 )
b11001110110011001100110010011101 1
#1450
1(
10
#1460
b11001110110011001100110010011101 6
b11001110110011001100110010011101 #
b11001110110011001100110010011101 4
b11001110110011001100110010011101 !
b11 %
b11 -
1(
10
#1470
b100 '
b100 /
b100 +
0(
00
#1480
b11001011001000000011111010010110 )
b11001011001000000011111010010110 1
#1490
1(
10
#1500
b11001011001000000011111010010110 6
b11001011001000000011111010010110 #
b11001011001000000011111010010110 4
b11001011001000000011111010010110 !
b100 %
b100 -
1(
10
#1510
b101 '
b101 /
b101 +
0(
00
#1520
b10001001100000111011100000010011 )
b10001001100000111011100000010011 1
#1530
1(
10
#1540
b10001001100000111011100000010011 6
b10001001100000111011100000010011 #
b10001001100000111011100000010011 4
b10001001100000111011100000010011 !
b101 %
b101 -
1(
10
#1550
b110 '
b110 /
b110 +
0(
00
#1560
b10000110101111000011100000001101 )
b10000110101111000011100000001101 1
#1570
1(
10
#1580
b10000110101111000011100000001101 6
b10000110101111000011100000001101 #
b10000110101111000011100000001101 4
b10000110101111000011100000001101 !
b110 %
b110 -
1(
10
#1590
b111 '
b111 /
b111 +
0(
00
#1600
b10101001101001111101011001010011 )
b10101001101001111101011001010011 1
#1610
1(
10
#1620
b10101001101001111101011001010011 6
b10101001101001111101011001010011 #
b10101001101001111101011001010011 4
b10101001101001111101011001010011 !
b111 %
b111 -
1(
10
#1630
b1000 '
b1000 /
b1000 +
0(
00
#1640
b110101100111111101110101101011 )
b110101100111111101110101101011 1
#1650
1(
10
#1660
b110101100111111101110101101011 6
b110101100111111101110101101011 #
b110101100111111101110101101011 4
b110101100111111101110101101011 !
b1000 %
b1000 -
1(
10
#1670
b1001 '
b1001 /
b1001 +
0(
00
#1680
b11101010101001100010101011010101 )
b11101010101001100010101011010101 1
#1690
1(
10
#1700
b11101010101001100010101011010101 6
b11101010101001100010101011010101 #
b11101010101001100010101011010101 4
b11101010101001100010101011010101 !
b1001 %
b1001 -
1(
10
#1710
b1010 '
b1010 /
b1010 +
0(
00
#1720
b10000001000101110100101000000010 )
b10000001000101110100101000000010 1
#1730
1(
10
#1740
b10000001000101110100101000000010 6
b10000001000101110100101000000010 #
b10000001000101110100101000000010 4
b10000001000101110100101000000010 !
b1010 %
b1010 -
1(
10
#1750
b1011 '
b1011 /
b1011 +
0(
00
#1760
b11010111010101100011111010101110 )
b11010111010101100011111010101110 1
#1770
1(
10
#1780
b11010111010101100011111010101110 6
b11010111010101100011111010101110 #
b11010111010101100011111010101110 4
b11010111010101100011111010101110 !
b1011 %
b1011 -
1(
10
#1790
b1100 '
b1100 /
b1100 +
0(
00
#1800
b1110111111111110100100011101 )
b1110111111111110100100011101 1
#1810
1(
10
#1820
b1110111111111110100100011101 6
b1110111111111110100100011101 #
b1110111111111110100100011101 4
b1110111111111110100100011101 !
b1100 %
b1100 -
1(
10
#1830
b1101 '
b1101 /
b1101 +
0(
00
#1840
b11100111110001010111001011001111 )
b11100111110001010111001011001111 1
#1850
1(
10
#1860
b11100111110001010111001011001111 6
b11100111110001010111001011001111 #
b11100111110001010111001011001111 4
b11100111110001010111001011001111 !
b1101 %
b1101 -
1(
10
#1870
b1110 '
b1110 /
b1110 +
0(
00
#1880
b10001100001000100100100100011 )
b10001100001000100100100100011 1
#1890
1(
10
#1900
b10001100001000100100100100011 6
b10001100001000100100100100011 #
b10001100001000100100100100011 4
b10001100001000100100100100011 !
b1110 %
b1110 -
1(
10
#1910
b1111 '
b1111 /
b1111 +
0(
00
#1920
b101000010010110010100001010 )
b101000010010110010100001010 1
#1930
1(
10
#1940
b101000010010110010100001010 6
b101000010010110010100001010 #
b101000010010110010100001010 4
b101000010010110010100001010 !
b1111 %
b1111 -
1(
10
#1950
b10000 '
b10000 /
b10000 +
0(
00
#1960
b11100101011100110000101011001010 )
b11100101011100110000101011001010 1
#1970
1(
10
#1980
b11100101011100110000101011001010 6
b11100101011100110000101011001010 #
b11100101011100110000101011001010 4
b11100101011100110000101011001010 !
b10000 %
b10000 -
1(
10
#1990
b10001 '
b10001 /
b10001 +
0(
00
#2000
b10011110001100010100110000111100 )
b10011110001100010100110000111100 1
#2010
1(
10
#2020
b10011110001100010100110000111100 6
b10011110001100010100110000111100 #
b10011110001100010100110000111100 4
b10011110001100010100110000111100 !
b10001 %
b10001 -
1(
10
#2030
b10010 '
b10010 /
b10010 +
0(
00
#2040
b1111001011010001011110111110010 )
b1111001011010001011110111110010 1
#2050
1(
10
#2060
b1111001011010001011110111110010 6
b1111001011010001011110111110010 #
b1111001011010001011110111110010 4
b1111001011010001011110111110010 !
b10010 %
b10010 -
1(
10
#2070
b10011 '
b10011 /
b10011 +
0(
00
#2080
b1000101001011100110000110001010 )
b1000101001011100110000110001010 1
#2090
1(
10
#2100
b1000101001011100110000110001010 6
b1000101001011100110000110001010 #
b1000101001011100110000110001010 4
b1000101001011100110000110001010 !
b10011 %
b10011 -
1(
10
#2110
b10100 '
b10100 /
b10100 +
0(
00
#2120
b100000110001001011001101000001 )
b100000110001001011001101000001 1
#2130
1(
10
#2140
b100000110001001011001101000001 6
b100000110001001011001101000001 #
b100000110001001011001101000001 4
b100000110001001011001101000001 !
b10100 %
b10100 -
1(
10
#2150
b10101 '
b10101 /
b10101 +
0(
00
#2160
b11101100010010110011010011011000 )
b11101100010010110011010011011000 1
#2170
1(
10
#2180
b11101100010010110011010011011000 6
b11101100010010110011010011011000 #
b11101100010010110011010011011000 4
b11101100010010110011010011011000 !
b10101 %
b10101 -
1(
10
#2190
b10110 '
b10110 /
b10110 +
0(
00
#2200
b111100001000001111001101111000 )
b111100001000001111001101111000 1
#2210
1(
10
#2220
b111100001000001111001101111000 6
b111100001000001111001101111000 #
b111100001000001111001101111000 4
b111100001000001111001101111000 !
b10110 %
b10110 -
1(
10
#2230
b10111 '
b10111 /
b10111 +
0(
00
#2240
b11000100100010100001001010001001 )
b11000100100010100001001010001001 1
#2250
1(
10
#2260
b11000100100010100001001010001001 6
b11000100100010100001001010001001 #
b11000100100010100001001010001001 4
b11000100100010100001001010001001 !
b10111 %
b10111 -
1(
10
#2270
b11000 '
b11000 /
b11000 +
0(
00
#2280
b1110101110001010000110111101011 )
b1110101110001010000110111101011 1
#2290
1(
10
#2300
b1110101110001010000110111101011 6
b1110101110001010000110111101011 #
b1110101110001010000110111101011 4
b1110101110001010000110111101011 !
b11000 %
b11000 -
1(
10
#2310
b11001 '
b11001 /
b11001 +
0(
00
#2320
b1011011000000100110010110110110 )
b1011011000000100110010110110110 1
#2330
1(
10
#2340
b1011011000000100110010110110110 6
b1011011000000100110010110110110 #
b1011011000000100110010110110110 4
b1011011000000100110010110110110 !
b11001 %
b11001 -
1(
10
#2350
b11010 '
b11010 /
b11010 +
0(
00
#2360
b1100011010010111111100111000110 )
b1100011010010111111100111000110 1
#2370
1(
10
#2380
b1100011010010111111100111000110 6
b1100011010010111111100111000110 #
b1100011010010111111100111000110 4
b1100011010010111111100111000110 !
b11010 %
b11010 -
1(
10
#2390
b11011 '
b11011 /
b11011 +
0(
00
#2400
b1010111000101010001001110101110 )
b1010111000101010001001110101110 1
#2410
1(
10
#2420
b1010111000101010001001110101110 6
b1010111000101010001001110101110 #
b1010111000101010001001110101110 4
b1010111000101010001001110101110 !
b11011 %
b11011 -
1(
10
#2430
b11100 '
b11100 /
b11100 +
0(
00
#2440
b11011110011101010000001010111100 )
b11011110011101010000001010111100 1
#2450
1(
10
#2460
b11011110011101010000001010111100 6
b11011110011101010000001010111100 #
b11011110011101010000001010111100 4
b11011110011101010000001010111100 !
b11100 %
b11100 -
1(
10
#2470
b11101 '
b11101 /
b11101 +
0(
00
#2480
b10101000011111101110100101010 )
b10101000011111101110100101010 1
#2490
1(
10
#2500
b10101000011111101110100101010 6
b10101000011111101110100101010 #
b10101000011111101110100101010 4
b10101000011111101110100101010 !
b11101 %
b11101 -
1(
10
#2510
b11110 '
b11110 /
b11110 +
0(
00
#2520
b10000101110101111001101000001011 )
b10000101110101111001101000001011 1
#2530
1(
10
#2540
b10000101110101111001101000001011 6
b10000101110101111001101000001011 #
b10000101110101111001101000001011 4
b10000101110101111001101000001011 !
b11110 %
b11110 -
1(
10
#2550
b11111 '
b11111 /
b11111 +
0(
00
#2560
b10111000100101111011111001110001 )
b10111000100101111011111001110001 1
#2570
1(
10
#2580
b10111000100101111011111001110001 7
b10111000100101111011111001110001 $
b10111000100101111011111001110001 6
b10111000100101111011111001110001 #
b10111000100101111011111001110001 4
b10111000100101111011111001110001 !
b11111 %
b11111 -
1(
10
#2590
b1001 '
b1001 /
b100000 +
0(
00
#2595
0(
00
b1100011 )
b1100011 1
#2600
b1100011 4
b1100011 !
b1001 %
b1001 -
