Entrega1/src/Comparator.v
module Comparator (a, b, op, compout);

	input 	[31:0]		a;
	input 	[31:0]	 	b;
	input 	[2:0] 		op;
	output 			compout;
	reg compout;

	always @(op or a or b)
	begin
		case (op)
			3'b000	: assign compout = a==b;
			3'b001	: assign compout = a>=b;
			3'b010	: assign compout = a<=b;
			3'b011	: assign compout = a>b;
			3'b100	: assign compout = a<b;
			3'b101	: assign compout = a!=b;
			//Caso não haja opcode compout será zero
			default	: assign compout = 1'b0;
		endcase
	end
endmodule

Entrega1/tb/tb_Comparator.v
module tb_Comparator;
reg [31:0] a;
reg [31:0] b;
reg [2:0] op;

wire compout;

//op=000 a==b
//op=001 a>=b
//op=010 a<=b
//op=011 a>b
//op=100 a<b
//op=101 a!=b

Comparator dut (a, b, op, compout);
initial
	begin
	$dumpfile("vcd/Comparator.vcd");
	$dumpvars;
	a = 32'b00000000000000000000000000000000;
	b = 32'b00000000000000000000000000000000;
	op= 3'b000;
	#10
	$display(compout);
	a = 32'b00000000000000000000000000000000;
	b = 32'b00000000000000000000000000000001;
	op= 3'b000;
	#10
	$display(compout);
	a = 32'b00000000000000000000000000000000;
	b = 32'b00000000000000000000000000000000;
	op= 3'b001;
	#10
	$display(compout);
	a = 32'b00000000000000000000000000000000;
	b = 32'b00000000000000000000000000000001;
	op= 3'b001;
	#10
	$display(compout);
	a = 32'b00000000000000000000000000000001;
	b = 32'b00000000000000000000000000000000;
	op= 3'b001;
	$display(compout);
	#10
	a = 32'b00000000000000000000000000000000;
	b = 32'b00000000000000000000000000000000;
	op= 3'b010;
	$display(compout);
	#10
	a = 32'b00000000000000000000000000000001;
	b = 32'b00000000000000000000000000000000;
	op= 3'b010;
	#10
	$display(compout);
	a = 32'b00000000000000000000000000000000;
	b = 32'b00000000000000000000000000000001;
	op= 3'b010;
	#10
	$display(compout);
	a = 32'b00000000000000000000000000000000;
	b = 32'b00000000000000000000000000000000;
	op= 3'b011;
	#10
	$display(compout);
	a = 32'b00000000000000000000000000000001;
	b = 32'b00000000000000000000000000000000;
	op= 3'b011;
	$display(compout);
	#10
	a = 32'b00000000000000000000000000000000;
	b = 32'b00000000000000000000000000000001;
	op= 3'b011;
	$display(compout);
	#10
	a = 32'b00000000000000000000000000000000;
	b = 32'b00000000000000000000000000000000;
	op= 3'b100;
	#10
	$display(compout);
	a = 32'b00000000000000000000000000000001;
	b = 32'b00000000000000000000000000000000;
	op= 3'b100;
	#10
	$display(compout);
	a = 32'b00000000000000000000000000000000;
	b = 32'b00000000000000000000000000000001;
	op= 3'b100;
	#10
	$display(compout);
	a = 32'b00000000000000000000000000000000;
	b = 32'b00000000000000000000000000000000;
	op= 3'b101;
	#10
	$display(compout);
	a = 32'b00000000000000000000000000000001;
	b = 32'b00000000000000000000000000000000;
	op= 3'b101;
	#10
	$display(compout);
	a = 32'b00000000000000000000000000000000;
	b = 32'b00000000000000000000000000000001;
	op= 3'b101;
	#10
	$display(compout);
	$finish;
	end
endmodule

Entrega1/vcd/Comparator.vcd
$date
	Sun Mar  9 12:05:55 2014
$end
$version
	Icarus Verilog
$end
$timescale
	1s
$end
$scope module tb_Comparator $end
$var wire 1 ! compout $end
$var reg 32 " a [31:0] $end
$var reg 32 # b [31:0] $end
$var reg 3 $ op [2:0] $end
$scope module dut $end
$var wire 32 % a [31:0] $end
$var wire 32 & b [31:0] $end
$var wire 3 ' op [2:0] $end
$var reg 1 ( compout $end
$upscope $end
$upscope $end
$enddefinitions $end
#0
$dumpvars
1(
b0 '
b0 &
b0 %
b0 $
b0 #
b0 "
1!
$end
#10
0(
0!
b1 #
b1 &
#20
1(
1!
b1 $
b1 '
b0 #
b0 &
#30
0(
0!
b1 #
b1 &
#40
1(
1!
b0 #
b0 &
b1 "
b1 %
#50
1(
b10 $
b10 '
b0 "
b0 %
#60
0(
0!
b1 "
b1 %
#70
1(
1!
b1 #
b1 &
b0 "
b0 %
#80
0(
0!
b11 $
b11 '
b0 #
b0 &
#90
1(
1!
b1 "
b1 %
#100
0(
0!
b1 #
b1 &
b0 "
b0 %
#110
0(
b100 $
b100 '
b0 #
b0 &
#120
0(
b1 "
b1 %
#130
1(
1!
b1 #
b1 &
b0 "
b0 %
#140
0(
0!
b101 $
b101 '
b0 #
b0 &
#150
1(
1!
b1 "
b1 %
#160
1(
b1 #
b1 &
b0 "
b0 %
