Entrega1/src/Alu.v
module Alu (
	input 	[31:0]		a,
	input 	[31:0]	 	b,
	output 	[31:0]		aluout,
	input 	[2:0]		op,
	input 			unsig,
	output 			compout,
	output 			overflow
);

	reg compout;
	reg overflow;
	reg [31:0] aluout;

	always @(op or a or b or unsig)
	begin
		case (op)
			3'b000	: aluout <= a&b;
			3'b001	: aluout <= a|b;
			3'b010	: begin
						aluout <= ($signed(a)+$signed(b));
						if (($signed(a)>=0)&&($signed(b)>=0)&&($signed(aluout)<0))
						begin
							overflow <= 1;
						end						
						else
						begin
							if (($signed(a)<0)&&($signed(b)<0)&&($signed(aluout)>=0))
							begin							
								overflow <= 1;
							end
							else
							begin
								overflow <= 0;
							end
						end
					end
			3'b100	: aluout <= ~(a|b);
			3'b101	: aluout <= a^b;
			3'b110	: begin
						aluout <= ($signed(a)-$signed(b));
						if (($signed(a)>=0)&&($signed(b)<0)&&($signed($signed(a)+$signed(b))<0))
						begin
							overflow <= 1;
						end						
						else
						begin
							if (($signed(a)<0)&&($signed(b)>=0)&&($signed($signed(a)+$signed(b))>=0))
							begin							
								overflow <= 1;
							end
							else
							begin
								overflow <= 0;
							end
						end
					end
			default	: aluout <= aluout; //tratar exceção 
		endcase
		if (unsig == 0)
		begin
			if (a<b)
			begin
				compout <= 1;
			end
			else
			begin
				compout <= 0;
			end
		end
		if (unsig == 1)
		begin
			if ($signed(a)<$signed(b))
			begin
				compout <= 1;
			end
			else
			begin
				compout <= 0;
			end
		end
	end
endmodule

Entrega1/tb/tb_Alu_dev.v
module Comparator_tb;

reg 	[31:0]		a;
reg 	[31:0]	 	b;
reg 	[2:0]		op;
reg 			unsig;
wire 			compout;
wire	overflow;
wire[31:0] aluout;

//op=000 a&&b
//op=001 a||b
//op=010 a+b
//op=100 a nor b
//op=101 a xor b
//op=110 a-b

Alu dut (a, b, aluout, op, unsig, compout, overflow);

initial
	begin
	$dumpfile("saidaComparator.vcd");
	$dumpvars;
	//a && b
	a = 32'b00000000000000000000000000000000;
	b = 32'b00000000000000000000000000000000;
	unsig = 2'b0;
	op=3'b000; 
	#10
	$display("%b",aluout);
	$display("%b",overflow);
	#10
	//a && b
	a = 32'b00000000000000000000000000000001;
	b = 32'b00000000000000000000000000000001;
	unsig = 2'b0;
	op=3'b000;
	#10
	$display("%b",aluout);
	$display("%b",overflow);
	#10
	//a || b
	a = 32'b00000000000000000000000000000000;
	b = 32'b00000000000000000000000000000001;
	unsig = 2'b0;
	op=3'b001;
	#10
	$display("%b",aluout);
	$display("%b",overflow);
	#10
	//a || b
	a = 32'b00000000000000000000000000000000;
	b = 32'b00000000000000000000000000000000;
	unsig = 2'b0;
	op=3'b001;
	#10
	$display("%b",aluout);
	$display("%b",overflow);
	#10
	//a + b
	a = 32'b00000000000000000000000000000000;
	b = 32'b00000000000000000000000000000000;
	unsig = 2'b0;
	op=3'b010;
	#10
	$display("%b",aluout);
	$display("%b",overflow);
	//a + b
	a = 32'b10000000000000000000000000000000;
	b = 32'b10000000000000000000000000000000;
	unsig = 2'b0;
	op=3'b010;
	#10
	$display("%b",aluout);
	$display("%b",overflow);
	//a + b
	a = 32'b00000000000000000000000000000001;
	b = 32'b00000000000000000000000000000001;
	unsig = 2'b0;
	op=3'b010;
	#10
	$display("%b",aluout);
	$display("%b",overflow);
	//a nor b
	a = 32'b00000000000000000000000000000001;
	b = 32'b00000000000000000000000000000001;
	unsig = 2'b0;
	op=3'b100;
	#10
	$display("%b",aluout);
	$display("%b",overflow);
	//a nor b
	a = 32'b00000000000000000000000000000000;
	b = 32'b00000000000000000000000000000000;
	unsig = 2'b0;
	op=3'b100;
	#10
	$display("%b",aluout);
	$display("%b",overflow);
	//a xnor b
	a = 32'b00000000000000000000000000000001;
	b = 32'b00000000000000000000000000000001;
	unsig = 2'b0;
	op=3'b101;
	#10
	$display("%b",aluout);
	$display("%b",overflow);
	//a xnor b
	a = 32'b00000000000000000000000000000001;
	b = 32'b00000000000000000000000000000000;
	unsig = 2'b0;
	op=3'b101;
	#10
	$display("%b",aluout);
	$display("%b",overflow);
	//a - b
	a = 32'b00000000000000000000000000000001;
	b = 32'b00000000000000000000000000000001;
	unsig = 2'b0;
	op=3'b110;
	#10
	$display("%b",aluout);
	$display("%b",overflow);
	//a - b
	a = 32'b00000000000000000000000000000000;
	b = 32'b00000000000000000000000000000001;
	unsig = 2'b0;
	op=3'b110;
	#10
	$display("%b",aluout);
	$display("%b",overflow);
	$finish;
	end
endmodule

Entrega1/src/saidaComparator.vcd
$date
	Sun Mar  9 09:28:49 2014
$end
$version
	Icarus Verilog
$end
$timescale
	1s
$end
$scope module Comparator_tb $end
$var wire 32 ! aluout [31:0] $end
$var wire 1 " compout $end
$var wire 1 # overflow $end
$var reg 32 $ a [31:0] $end
$var reg 32 % b [31:0] $end
$var reg 3 & op [2:0] $end
$var reg 1 ' unsig $end
$scope module dut $end
$var wire 32 ( a [31:0] $end
$var wire 32 ) b [31:0] $end
$var wire 3 * op [2:0] $end
$var wire 1 + unsig $end
$var reg 32 , aluout [31:0] $end
$var reg 1 - compout $end
$var reg 1 . overflow $end
$upscope $end
$upscope $end
$enddefinitions $end
#0
$dumpvars
x.
0-
b0 ,
0+
b0 *
b0 )
b0 (
0'
b0 &
b0 %
b0 $
x#
0"
b0 !
$end
#20
b1 ,
b1 !
b1 %
b1 )
b1 $
b1 (
#40
1-
1"
b1 ,
b1 &
b1 *
b0 $
b0 (
#60
0-
0"
b0 ,
b0 !
b0 %
b0 )
#80
0.
0#
b0 ,
b10 &
b10 *
#90
1.
1#
b0 ,
b10000000000000000000000000000000 %
b10000000000000000000000000000000 )
b10000000000000000000000000000000 $
b10000000000000000000000000000000 (
#100
0.
0#
b10 ,
b10 !
b1 %
b1 )
b1 $
b1 (
#110
b11111111111111111111111111111110 ,
b11111111111111111111111111111110 !
b100 &
b100 *
#120
b11111111111111111111111111111111 ,
b11111111111111111111111111111111 !
b0 %
b0 )
b0 $
b0 (
#130
b0 ,
b0 !
b101 &
b101 *
b1 %
b1 )
b1 $
b1 (
#140
b1 ,
b1 !
b0 %
b0 )
#150
0.
b0 ,
b0 !
b110 &
b110 *
b1 %
b1 )
#160
1-
1"
0.
b11111111111111111111111111111111 ,
b11111111111111111111111111111111 !
b0 $
b0 (
