Entrega1/src/Shifter.v
module Shifter(
	input [31:0] in,
	input [1:0] shiftop,
	input [4:0] shiftamt,
	output [31:0] result	
);
	
	reg [31:0] result;
	always @(in or shiftamt or shiftop)
			begin
				case(shiftop)
					2'b00 : result = in >> shiftamt;
					2'b01 : result = in >>> shiftamt;
					2'b10 : result = in << shiftamt;					
				endcase
			end
endmodule

Entrega1/src/Shifter_tb.v
module Shifter_tb;

reg [31:0] in;
reg [1:0] shiftop;
reg [4:0] shiftamt;
wire [31:0] result;


//shiftop = 00 shift lógico para direita
//shiftop = 01 shift aritmético para direita
//shiftop = 10 shift lógico para esquerda

Shifter teste(in,shiftop,shiftamt, result);

initial
	begin
	$dumpfile("Shifter.vcd");
	$dumpvars;
	in=32'b00000000000000000000000000000001;
	shiftop=2'b00;
	shiftamt=4'b0001;
	#10
	$display("%b",result);
	in=32'b00000000000000000000000000000001;
	shiftop=2'b00;
	shiftamt=4'b0010;
	#10
	$display("%b",result);
	in=32'b00000000000000000000000000000001;
	shiftop=2'b00;
	shiftamt=4'b0011;
	#10
	$display("%b",result);
	in=32'b00000000000000000000000000000001;
	shiftop=2'b01;
	shiftamt=4'b0001;
	#10
	$display("%b",result);
	in=32'b00000000000000000000000000000001;
	shiftop=2'b01;
	shiftamt=4'b0010;
	#10
	$display("%b",result);
	in=32'b00000000000000000000000000000001;
	shiftop=2'b01;
	shiftamt=4'b0011;
	#10
	$display("%b",result);
	in=32'b00000000000000000000000000000001;
	shiftop=2'b10;
	shiftamt=4'b0001;
	#10
	$display("%b",result);
	in=32'b00000000000000000000000000000001;
	shiftop=2'b10;
	shiftamt=4'b0010;
	#10
	$display("%b",result);
	in=32'b00000000000000000000000000000001;
	shiftop=2'b10;
	shiftamt=4'b0011;
	#10
	$display("%b",result);
	$finish;
	end
endmodule

Entrega1/src/Shifter.vcd
$date
	Sun Mar  9 09:40:27 2014
$end
$version
	Icarus Verilog
$end
$timescale
	1s
$end
$scope module Shifter_tb $end
$var wire 32 ! result [31:0] $end
$var reg 32 " in [31:0] $end
$var reg 5 # shiftamt [4:0] $end
$var reg 2 $ shiftop [1:0] $end
$scope module teste $end
$var wire 32 % in [31:0] $end
$var wire 5 & shiftamt [4:0] $end
$var wire 2 ' shiftop [1:0] $end
$var reg 32 ( result [31:0] $end
$upscope $end
$upscope $end
$enddefinitions $end
#0
$dumpvars
b0 (
b0 '
b1 &
b1 %
b0 $
b1 #
b1 "
b0 !
$end
#10
b10 #
b10 &
#20
b11 #
b11 &
#30
b1 #
b1 &
b1 $
b1 '
#40
b10 #
b10 &
#50
b11 #
b11 &
#60
b10 (
b10 !
b1 #
b1 &
b10 $
b10 '
#70
b100 (
b100 !
b10 #
b10 &
#80
b1000 (
b1000 !
b11 #
b11 &
