Entrega5/src/Ram.v
module Ram (
    input    [17:0]    addr,
    inout    [15:0]    data,
    input              wre,
    input              oute,
    input              hb_mask,
    input              lb_mask,
    input              chip_en
);

    reg     [15:0]    memory    [0:262143];
    reg     [15:0]    d;
    wire    [15:0]    q;

    integer i;

    assign q = memory[addr];
    assign data[7:0]  = (!chip_en && !oute && !lb_mask) ? q[7:0] : 8'hZZ;
    assign data[15:8] = (!chip_en && !oute && !hb_mask) ? q[15:8] : 8'hZZ;

    always @(chip_en or wre or hb_mask or lb_mask or addr or data or d) begin
        if (!chip_en && !wre) begin
            d[15:0] = memory[addr];
            if (!hb_mask) begin
                d[15:8] = data[15:8];
            end
            if (!lb_mask) begin
                d[7:0] = data[7:0];
            end
            memory[addr] = d[15:0];
        end
    end
endmodule

Entrega3/src/MemControler.v
module MemControler(clock, reset, if_mc_en, if_mc_addr, mc_if_data, mem_mc_rw, mem_mc_en, mem_mc_addr, mem_mc_data, mc_ram_addr, mc_ram_wre, mc_ram_data);
	input clock; //acesso a ram na subida
	input reset; // coloca todos os regs em 0 na descida
	
	// Fetch
	input if_mc_en; //indica qual estágio de BuscInstr
	input [17:0] if_mc_addr; //endereço acessado pelo estágio de BuscInstr
	output [31:0] mc_if_data; //dado completo lido da RAM a ser enviado para a unidade de BuscInstr
	
	// Memory
	input mem_mc_rw; //indica quando instrução no estágio de memória escreve na RAM
	input mem_mc_en; //indica quando instrução no estágio de memória acessa a RAM. 
			// esse acesso tem prioridade sobre acessos feitos pelo estágio de BuscInstr
			//deve estar em zero, mesmo com if_mc_en igual a 1
	input [17:0] mem_mc_addr; //endereço acessado pelo estágio de Memória
	inout [31:0] mem_mc_data; //dado completo 1)lido da RAM --> a ser enviado para estágio de Memória
				//2) recebido do estágio de Memória --> a ser escrito na RAM
	
	// Ram
	output [17:0] mc_ram_addr; //endereço da ram no qual o acesso será feito. (ver detalhe sobre addr/2)
	output mc_ram_wre;//quando em 0 indica que a operação na RAM será de escrita
			//operação só é de leitura quando: ((!mem_mc_en & if_mc_en) | !mem_mc_rw)
	
	
	inout [15:0] mc_ram_data; //metade do dado a ser lido/enviado na RAM.
	
	// Auxilares
	reg zero = 0;
	reg [17:0] ram_addr;
	reg [15:0] data1;
	reg [31:0] data2;
	reg [31:0] data3;
	reg conta_clock=1;
	integer cont;

assign mc_ram_wre = ((!mem_mc_en & if_mc_en) | (!mem_mc_rw));	

assign mc_ram_addr = ram_addr;

assign mc_ram_data = data1;

assign mem_mc_data = data2;

assign mc_if_data = data3;

// Reset assíncrono
always @(posedge clock or negedge reset )begin
	if(~reset) begin
		for( cont = 0; cont < 17; cont = cont +1) begin
			ram_addr[cont] = 18'b0;
		end
		for(cont =0; cont < 15; cont = cont+1) begin
			data1[cont] = 16'b0;
		end
		for(cont =0; cont < 31; cont = cont+1) begin
			data2[cont] = 32'b0;
			data3[cont] = 32'b0;
		end
	end
	else begin
		// Se for uma operação de leitura.
		if(mc_ram_wre) begin
			// Quem vai ler é o estágio de leitura.
			if(mem_mc_en) begin
				if(conta_clock) begin
					// Convertendo para ser lido pela FPGA.
					ram_addr <= (mem_mc_addr >>1);
					data2[31:16] <= data1;
					ram_addr<= ram_addr +1;
					conta_clock <= ~conta_clock;
				end
				else begin
					// Dando um clock entre as instruções.
					data2[15:0]<= data1;
					conta_clock <= ~conta_clock;
				end
			end
			// Quem vai ler é o estágio de fetch.
			else begin
				if(conta_clock) begin
					ram_addr <= (if_mc_addr >> 1);
					data3[31:16] <= data1;
					ram_addr<= ram_addr +1;
					conta_clock <= ~conta_clock;
				end
				else begin
					// Dando um clock entre as instruções.
					data3[15:0] <= data1;
					conta_clock <= ~conta_clock;
				end
			end
		end
		else begin
			if(conta_clock) begin
				ram_addr <= (mem_mc_addr >> 1);
				data1 <= data2[31:16];
				ram_addr<= ram_addr +1;
				conta_clock <= ~conta_clock;
			end
			else begin
				// Dando um clock entre as instruções.
				data1 <= data2[15:0];
				conta_clock <= ~conta_clock;
			end
		end
	end
end

endmodule

Entrega3/tb/MemControler_tb.v
/* sudolshw@gmail.com */

module MemControler_tb();
    reg clock, reset, if_mc_en; //input -> reg
    reg [17:0] if_mc_addr;
    wire [31:0] mc_if_data; //output -> wire
    reg mem_mc_rw, mem_mc_en;
    reg [17:0] mem_mc_addr;
    inout [31:0] mem_mc_data; //inout -> ?
    wire [17:0] mc_ram_addr;
    wire mc_ram_wre;
    inout [15:0] mc_ram_data;

	parameter begin_time = 0;
	parameter clock_time = 10;
	parameter write_time_case1 = 100; //!mem_mc_en & if_mc_en
	parameter reset_time1 = 160;
	parameter write_time_case2 = 200; //!mem_mc_rw
	parameter finishtime = 300;

	initial begin
		$dumpfile ("vcd/MemControler.vcd");
		$dumpvars;
		clock <= 1'b1;
		reset <= 1'b0; 
		forever begin
			#clock_time clock = ~clock;
		end
	end

	initial
		#finishtime $finish;

    always @(posedge clock or negedge reset )begin
        $display ("----------------------------------------------------------------");
		$display ("Time = %d Reset = %d mc_if_data = %d",  $time, reset, mc_if_data);
		
		case ($time) 
			begin_time: reset <= 1'b0;
			write_time_case1: begin //!mem_mc_en & if_mc_en
                $display ("write_time_case1");
                mem_mc_en <= 1'b1;
                if_mc_en <= 1'b1; 
                //TODO: efeito não esperado em mc_ram_wre --> x ao invés de 1
            end
			reset_time1:  begin
			    $display ("reseting...");
			    reset <= 1'b0;
			end
            write_time_case2: begin //!mem_mc_rw
                $display ("write_time_case2");
                mem_mc_rw <= 1'b1;
            end
			1: begin
				reset <= 1'b1;
		    end
		endcase
	
		$display ("if_mc_en = %d", if_mc_en);
		//$display ("if_mc_addr = %d", if_mc_addr);  
		//$display ("mc_if_data = %d", mc_if_data);
		//$display ("mem_mc_rw = %d", mem_mc_rw);
		$display ("mem_mc_en = %d", mem_mc_en);
		//$display ("mem_mc_addr = %d",mem_mc_addr);
		//$display ("mem_mc_data = %d",mem_mc_data);
		//$display ("mc_ram_addr = %d", mc_ram_addr);
		$display ("mc_ram_wre = %d  ", mc_ram_wre);
		//$display ("mc_ram_data = %d", mc_ram_data);
	end

	MemControler dut (.clock(clock), .reset(reset), 
            .if_mc_en(if_mc_en), .if_mc_addr(if_mc_addr), .mc_if_data(mc_if_data), 
            .mem_mc_rw(mem_mc_rw), .mem_mc_en(mem_mc_en), .mem_mc_addr(mem_mc_addr), .mem_mc_data(mem_mc_data), 
            .mc_ram_addr(mc_ram_addr), .mc_ram_wre(mc_ram_wre), .mc_ram_data(mc_ram_data));

endmodule

Entrega3/MemControler.vcd
$date
	Fri Apr 11 08:54:41 2014
$end
$version
	Icarus Verilog
$end
$timescale
	1s
$end
$scope module MemControler_tb $end
$var wire 32 ! mc_if_data [31:0] $end
$var wire 18 " mc_ram_addr [17:0] $end
$var wire 16 # mc_ram_data [15:0] $end
$var wire 1 $ mc_ram_wre $end
$var wire 32 % mem_mc_data [31:0] $end
$var reg 1 & clock $end
$var reg 18 ' if_mc_addr [17:0] $end
$var reg 1 ( if_mc_en $end
$var reg 18 ) mem_mc_addr [17:0] $end
$var reg 1 * mem_mc_en $end
$var reg 1 + mem_mc_rw $end
$var reg 1 , reset $end
$scope module dut $end
$var wire 1 - clock $end
$var wire 18 . if_mc_addr [17:0] $end
$var wire 1 / if_mc_en $end
$var wire 32 0 mc_if_data [31:0] $end
$var wire 18 1 mc_ram_addr [17:0] $end
$var wire 16 2 mc_ram_data [15:0] $end
$var wire 1 $ mc_ram_wre $end
$var wire 18 3 mem_mc_addr [17:0] $end
$var wire 32 4 mem_mc_data [31:0] $end
$var wire 1 5 mem_mc_en $end
$var wire 1 6 mem_mc_rw $end
$var wire 1 7 reset $end
$var integer 32 8 cont [31:0] $end
$var reg 1 9 conta_clock $end
$var reg 16 : data1 [15:0] $end
$var reg 32 ; data2 [31:0] $end
$var reg 32 < data3 [31:0] $end
$var reg 18 = ram_addr [17:0] $end
$var reg 1 > zero $end
$upscope $end
$upscope $end
$scope module Ram $end
$var wire 18 ? addr [17:0] $end
$var wire 1 @ chip_en $end
$var wire 16 A data [15:0] $end
$var wire 1 B hb_mask $end
$var wire 1 C lb_mask $end
$var wire 1 D oute $end
$var wire 16 E q [15:0] $end
$var wire 1 F wre $end
$var reg 16 G d [15:0] $end
$upscope $end
$enddefinitions $end
#0
$dumpvars
bx G
zF
bx E
zD
zC
zB
bx A
z@
bz ?
0>
bx00000000000000000 =
bx0000000000000000000000000000000 <
bx0000000000000000000000000000000 ;
bx000000000000000 :
19
b11111 8
07
x6
x5
bx0000000000000000000000000000000 4
bx 3
bx000000000000000 2
bx00000000000000000 1
bx0000000000000000000000000000000 0
x/
bx .
1-
0,
x+
x*
bx )
x(
bx '
1&
bx0000000000000000000000000000000 %
x$
bx000000000000000 #
bx00000000000000000 "
bx0000000000000000000000000000000 !
$end
#10
0&
0-
#20
bx0000000000000000000000000000000 <
bx0000000000000000000000000000000 ;
bx000000000000000 :
bx00000000000000000 =
b11111 8
1&
1-
#30
0&
0-
#40
bx0000000000000000000000000000000 <
bx0000000000000000000000000000000 ;
bx000000000000000 :
bx00000000000000000 =
b11111 8
1&
1-
#50
0&
0-
#60
bx0000000000000000000000000000000 <
bx0000000000000000000000000000000 ;
bx000000000000000 :
bx00000000000000000 =
b11111 8
1&
1-
#70
0&
0-
#80
bx0000000000000000000000000000000 <
bx0000000000000000000000000000000 ;
bx000000000000000 :
bx00000000000000000 =
b11111 8
1&
1-
#90
0&
0-
#100
0(
0/
0*
05
bx0000000000000000000000000000000 <
bx0000000000000000000000000000000 ;
bx000000000000000 :
bx00000000000000000 =
b11111 8
1&
1-
#110
0&
0-
#120
bx0000000000000000000000000000000 <
bx0000000000000000000000000000000 ;
bx000000000000000 :
bx00000000000000000 =
b11111 8
1&
1-
#130
0&
0-
#140
bx0000000000000000000000000000000 <
bx0000000000000000000000000000000 ;
bx000000000000000 :
bx00000000000000000 =
b11111 8
1&
1-
#150
0&
0-
#160
bx0000000000000000000000000000000 <
bx0000000000000000000000000000000 ;
bx000000000000000 :
bx00000000000000000 =
b11111 8
1&
1-
#170
0&
0-
#180
bx0000000000000000000000000000000 <
bx0000000000000000000000000000000 ;
bx000000000000000 :
bx00000000000000000 =
b11111 8
1&
1-
#190
0&
0-
#200
1$
0+
06
bx0000000000000000000000000000000 <
bx0000000000000000000000000000000 ;
bx000000000000000 :
bx00000000000000000 =
b11111 8
1&
1-
#210
0&
0-
#220
bx0000000000000000000000000000000 <
bx0000000000000000000000000000000 ;
bx000000000000000 :
bx00000000000000000 =
b11111 8
1&
1-
#230
0&
0-
#240
bx0000000000000000000000000000000 <
bx0000000000000000000000000000000 ;
bx000000000000000 :
bx00000000000000000 =
b11111 8
1&
1-
#250
0&
0-
#260
bx0000000000000000000000000000000 <
bx0000000000000000000000000000000 ;
bx000000000000000 :
bx00000000000000000 =
b11111 8
1&
1-
#270
0&
0-
#280
bx0000000000000000000000000000000 <
bx0000000000000000000000000000000 ;
bx000000000000000 :
bx00000000000000000 =
b11111 8
1&
1-
#290
0&
0-
#300
bx0000000000000000000000000000000 <
bx0000000000000000000000000000000 ;
bx000000000000000 :
bx00000000000000000 =
b11111 8
1&
1-
#310
0&
0-
#320
bx0000000000000000000000000000000 <
bx0000000000000000000000000000000 ;
bx000000000000000 :
bx00000000000000000 =
b11111 8
1&
1-
#330
0&
0-
#340
bx0000000000000000000000000000000 <
bx0000000000000000000000000000000 ;
bx000000000000000 :
bx00000000000000000 =
b11111 8
1&
1-
#350
0&
0-
#360
bx0000000000000000000000000000000 <
bx0000000000000000000000000000000 ;
bx000000000000000 :
bx00000000000000000 =
b11111 8
1&
1-
#370
0&
0-
#380
bx0000000000000000000000000000000 <
bx0000000000000000000000000000000 ;
bx000000000000000 :
bx00000000000000000 =
b11111 8
1&
1-
#390
0&
0-
#400
bx0000000000000000000000000000000 <
bx0000000000000000000000000000000 ;
bx000000000000000 :
bx00000000000000000 =
b11111 8
1&
1-
#410
0&
0-
#420
bx0000000000000000000000000000000 <
bx0000000000000000000000000000000 ;
bx000000000000000 :
bx00000000000000000 =
b11111 8
1&
1-
#430
0&
0-
#440
bx0000000000000000000000000000000 <
bx0000000000000000000000000000000 ;
bx000000000000000 :
bx00000000000000000 =
b11111 8
1&
1-
#450
0&
0-
#460
bx0000000000000000000000000000000 <
bx0000000000000000000000000000000 ;
bx000000000000000 :
bx00000000000000000 =
b11111 8
1&
1-
#470
0&
0-
#480
bx0000000000000000000000000000000 <
bx0000000000000000000000000000000 ;
bx000000000000000 :
bx00000000000000000 =
b11111 8
1&
1-
#490
0&
0-
#500
bx0000000000000000000000000000000 <
bx0000000000000000000000000000000 ;
bx000000000000000 :
bx00000000000000000 =
b11111 8
1&
1-
#510
0&
0-
#520
bx0000000000000000000000000000000 <
bx0000000000000000000000000000000 ;
bx000000000000000 :
bx00000000000000000 =
b11111 8
1&
1-
#530
0&
0-
#540
bx0000000000000000000000000000000 <
bx0000000000000000000000000000000 ;
bx000000000000000 :
bx00000000000000000 =
b11111 8
1&
1-
#550
0&
0-
#560
bx0000000000000000000000000000000 <
bx0000000000000000000000000000000 ;
bx000000000000000 :
bx00000000000000000 =
b11111 8
1&
1-
#570
0&
0-
#580
bx0000000000000000000000000000000 <
bx0000000000000000000000000000000 ;
bx000000000000000 :
bx00000000000000000 =
b11111 8
1&
1-
#590
0&
0-
#600
bx0000000000000000000000000000000 <
bx0000000000000000000000000000000 ;
bx000000000000000 :
bx00000000000000000 =
b11111 8
1&
1-
