Entrega1/src/Alu.v
module Alu (
	input 	[31:0]		a,
	input 	[31:0]	 	b,
	output 	[31:0]		aluout,
	input 	[2:0]		op,
	input 			unsig,
	output 			compout,
	output 			overflow
);

	reg compout;
	reg overflow;
	reg [31:0] aluout;

	always @(op or a or b or unsig)
	begin
		case (op)
			3'b000	: aluout <= a&b;
			3'b001	: aluout <= a|b;
			3'b010	: begin
						aluout <= ($signed(a)+$signed(b));
						if (($signed(a)>=0)&&($signed(b)>=0)&&($signed(aluout)<0))
						begin
							overflow <= 1;
						end						
						else
						begin
							if (($signed(a)<0)&&($signed(b)<0)&&($signed(aluout)>=0))
							begin							
								overflow <= 1;
							end
							else
							begin
								overflow <= 0;
							end
						end
					end
			3'b100	: aluout <= ~(a|b);
			3'b101	: aluout <= a^b;
			3'b110	: begin
						aluout <= ($signed(a)-$signed(b));
						if (($signed(a)>=0)&&($signed(b)<0)&&($signed($signed(a)+$signed(b))<0))
						begin
							overflow <= 1;
						end						
						else
						begin
							if (($signed(a)<0)&&($signed(b)>=0)&&($signed($signed(a)+$signed(b))>=0))
							begin							
								overflow <= 1;
							end
							else
							begin
								overflow <= 0;
							end
						end
					end
			default	: aluout <= aluout; //tratar exceção 
		endcase
		if (unsig == 0)
		begin
			if (a<b)
			begin
				compout <= 1;
			end
			else
			begin
				compout <= 0;
			end
		end
		if (unsig == 1)
		begin
			if ($signed(a)<$signed(b))
			begin
				compout <= 1;
			end
			else
			begin
				compout <= 0;
			end
		end
	end
endmodule

Entrega1/tb/tb_Alu.v
`include "Alu.v"

/*Teste operação de soma da Alu*/
module tb_Alu ();
	
	/*---------------------------------------	Alu Regs	----------------------------*/
	
	reg 	[31:0] 	a,b;
	reg	[2:0]  	op [5:0] ;
	reg		unsig;
	reg		clk;//clock para facilitar a criação dos testbenchs;
	reg	[32:0]	overflow_checker[1:0]; /*checar overflow das operações unsigneds*/	
	
	
	
	/*--------------------------------------- 		Op	----------------------------*/
	
	//op=000 a&&b 
	//op=001 a||b 
	//op=010 a+b  ****teste
	//op=100 a nor b
	//op=101 a xor b
	//op=110 a-b

	/*---------------------------------------	Alu Wires	---------------------------*/
	wire 		compout;
	wire	[5:0]	overflow;
	wire	[31:0]	aluout	[5:0];
	
	/*-----	Parameters Declaration : initialt time 0, delay of 5 and finishes at 500  ---------*/
	 
	parameter initialtime = 0;
	parameter delay = 5;
	parameter finishtime = 200;
		
	

	initial begin
	
		$dumpfile ("alu.vcd");
		$dumpvars;

		#initialtime
		clk 	<= 	1'b1;
		unsig 	<=	1'b1;	//signed operation
		op[0]	=	3'b000;
		op[1]	=	3'b001;
		op[2] 	=	3'b010;
		op[3]	=	3'b100;
		op[4]	=	3'b101;
		op[5] 	= 	3'b110;	
		
	end	
initial 
		#finishtime $finish;
		
always begin

	#delay clk = ~clk;

end
/*-------------------------------------------------------------------------setting variables-----------------------------------------------------------*/
always @(posedge clk) begin

	b <= $random;
	a <= $random;/*adder*/
	unsig <= ~unsig;
	
	$display ("time:%d,clk: %b, unsig: %b ,compout: %b", $time, clk, unsig, compout);
	
	if (unsig == 1) begin
	
		$display ("Input A: %b(%d), Input B: %b(%d) ", a,$signed(a),b,$signed(b));
	
	end
	
	else begin
	
		$display ("Input A: %b(%d), Input B: %b(%d) ", a,a,b,b);
	
	end


/*   --------------------------------------------------------------------- And--------------------------------------------------------------------------*/	

	
		$display ("And: %b ", op[0]);
			
		$display  ("aluout_and: %b",aluout[0]);/*soma e subtração, checando com binarios */



/*   --------------------------------------------------------------------- Or--------------------------------------------------------------------------*/	

	
		$display ("Or: %b ",op[1]);
	
		$display  ("aluout_or: %b",aluout[1]);/*soma e subtração, checando com binarios */

	

/*   --------------------------------------------------------------------- ADDER --------------------------------------------------------------------------*/	

		
		$display ("Adder: %b",op[2]);
		/* -------------------------------------------------------------Números sem sinais----------------------------------------------------------------*/
		if (unsig == 0 ) begin

		
				overflow_checker[0] = a+b;/*vetor de 33 bits, verifica se houve overflow com os valores unsigneds*/
		
			if ($signed (overflow_checker[0]) < 0 ) begin
		
				$display ("overflow_checker: %d we had overflow", overflow_checker[0]);
			
			end
			
			else begin
			
				$display ("no overflow");
				
			end
		
			$display  ("aluout_adder_unsigned: %b(%d),  overflow: %b ", aluout[2],aluout[2] ,overflow[2]);

		end
		
		/* -------------------------------------------------------------Números com sinais----------------------------------------------------------------*/
		else begin
	
			if ( ($signed(a) >= 0 && $signed (b) >= 0 && $signed (aluout[2]) < 0) ||  ( $signed(a) < 0  && $signed(b) < 0 && $signed(aluout[2]) >= 0) ) begin
		
				$display ("we had overflow ");
		
			end
		
			else begin
			
				$display ("no overflow");
			
			end
			
			$display  ("aluout_adder_signed: %b(%d), overflow: %b ", $signed(aluout[2]), $signed(aluout[2]),overflow[2]);/*soma e subtração, checando com binarios */
		
		end

	

/*   --------------------------------------------------------------------- Nor--------------------------------------------------------------------------*/	

	
		$display ("Nor: %b",op[3]);
	
		$display  (" aluout_nor: %b", aluout[3] );/*soma e subtração, checando com binarios */

	

/*   --------------------------------------------------------------------- Xor--------------------------------------------------------------------------*/

	
		$display ("Xor: %b ",op[4]);
	
		$display  (" aluout_xor: %b",aluout[4] );/*soma e subtração, checando com binarios */



/*   --------------------------------------------------------------------- Sub--------------------------------------------------------------------------*/

	
		$display ("Sub: %b",op[5]);
	/* -------------------------------------------------------------Números sem sinais----------------------------------------------------------------*/
		if (unsig == 0 ) begin

			overflow_checker[1] = a-b;/*vetor de 33 bits, verifica se houve overflow com os valores unsigneds*/
		
			if ($signed (overflow_checker[1]) < 0 ) begin
		
				$display ("overflow_checker: %d we had overflow", $signed(overflow_checker[1]) );
			
			end
			
			else begin
			
				$display ("no overflow");
				
			end
		
			$display  ("aluout_sub_unsigned: %b(%d), overflow: %b ",aluout[5],aluout[5] ,overflow[5]);/*soma e subtração, checando com binarios */
		
		end
		
		/* -------------------------------------------------------------Números com sinais----------------------------------------------------------------*/
		else begin
				
			$display ("signed number");
			
			if ( ($signed(a) >= 0 && $signed (b) < 0 && $signed (aluout[5]) < 0) ||  ( $signed(a) < 0  && $signed(b) >= 0 && $signed(aluout[5]) >= 0) ) begin
		
				$display ("we had overflow");
		
			end
		
			else begin
			
				$display ("no overflow");
			
			end
			
			$display  ("aluout_sub_signed: %b(%d), overflow: %b ", $signed(aluout[5]), $signed(aluout[5]), overflow[5]);/*soma e subtração, checando com binarios */		
			
		end
		
		$display ("----------------------------------------------*************Next Numbers*************------------------------------------------------");
		

end	

		Alu A_N_D (.a(a), .b(b), .aluout(aluout[0]), .op(op[0]), .unsig(unsig), .compout(compout), .overflow(overflow[0]));
		Alu O_R (.a(a), .b(b), .aluout(aluout[1]), .op(op[1]), .unsig(unsig), .compout(compout), .overflow(overflow[1]));
		Alu A_D_D (.a(a), .b(b), .aluout(aluout[2]), .op(op[2]), .unsig(unsig), .compout(compout), .overflow(overflow[2]));
		Alu N_O_R (.a(a), .b(b), .aluout(aluout[3]), .op(op[3]), .unsig(unsig), .compout(compout), .overflow(overflow[3]));
		Alu X_O_R (.a(a), .b(b), .aluout(aluout[4]), .op(op[4]), .unsig(unsig), .compout(compout), .overflow(overflow[4]));
		Alu S_U_B (.a(a), .b(b), .aluout(aluout[5]), .op(op[5]), .unsig(unsig), .compout(compout), .overflow(overflow[5]));
endmodule

Entrega1/alu.vcd
$date
	Fri May  2 15:04:16 2014
$end
$version
	Icarus Verilog
$end
$timescale
	10ps
$end
$scope module tb_Alu $end
$var wire 1 ! compout $end
$var wire 6 " overflow [5:0] $end
$var reg 32 # a [31:0] $end
$var reg 32 $ b [31:0] $end
$var reg 1 % clk $end
$var reg 1 & unsig $end
$scope module A_N_D $end
$var wire 32 ' a [31:0] $end
$var wire 32 ( b [31:0] $end
$var wire 3 ) op [2:0] $end
$var wire 1 * unsig $end
$var reg 32 + aluout [31:0] $end
$var reg 1 , compout $end
$var reg 1 - overflow $end
$upscope $end
$scope module O_R $end
$var wire 32 . a [31:0] $end
$var wire 32 / b [31:0] $end
$var wire 3 0 op [2:0] $end
$var wire 1 * unsig $end
$var reg 32 1 aluout [31:0] $end
$var reg 1 2 compout $end
$var reg 1 3 overflow $end
$upscope $end
$scope module A_D_D $end
$var wire 32 4 a [31:0] $end
$var wire 32 5 b [31:0] $end
$var wire 3 6 op [2:0] $end
$var wire 1 * unsig $end
$var reg 32 7 aluout [31:0] $end
$var reg 1 8 compout $end
$var reg 1 9 overflow $end
$upscope $end
$scope module N_O_R $end
$var wire 32 : a [31:0] $end
$var wire 32 ; b [31:0] $end
$var wire 3 < op [2:0] $end
$var wire 1 * unsig $end
$var reg 32 = aluout [31:0] $end
$var reg 1 > compout $end
$var reg 1 ? overflow $end
$upscope $end
$scope module X_O_R $end
$var wire 32 @ a [31:0] $end
$var wire 32 A b [31:0] $end
$var wire 3 B op [2:0] $end
$var wire 1 * unsig $end
$var reg 32 C aluout [31:0] $end
$var reg 1 D compout $end
$var reg 1 E overflow $end
$upscope $end
$scope module S_U_B $end
$var wire 32 F a [31:0] $end
$var wire 32 G b [31:0] $end
$var wire 3 H op [2:0] $end
$var wire 1 * unsig $end
$var reg 32 I aluout [31:0] $end
$var reg 1 J compout $end
$var reg 1 K overflow $end
$upscope $end
$upscope $end
$enddefinitions $end
#0
$dumpvars
0K
0J
b10101110011101000010100101011101 I
b110 H
b10010000101010011010100100100 G
b11000000100010010101111010000001 F
xE
0D
b11010010100111000110101110100101 C
b101 B
b10010000101010011010100100100 A
b11000000100010010101111010000001 @
x?
0>
b101101011000101000000001011010 =
b100 <
b10010000101010011010100100100 ;
b11000000100010010101111010000001 :
09
08
b11010010100111101001001110100101 7
b10 6
b10010000101010011010100100100 5
b11000000100010010101111010000001 4
x3
02
b11010010100111010111111110100101 1
b1 0
b10010000101010011010100100100 /
b11000000100010010101111010000001 .
x-
0,
b10001010000000000 +
0*
b0 )
b10010000101010011010100100100 (
b11000000100010010101111010000001 '
0&
1%
b10010000101010011010100100100 $
b11000000100010010101111010000001 #
b0xx0xx "
0!
$end
#500
0%
#1000
b101101011010111000000001011010 I
b110101011101001000000001101010 C
b1001010000010110010100110010100 =
b110110011101010010110001101100 7
b10110101111101001101011001101011 1
b10000000100000000101011000000001 +
1&
1*
b10110001111100000101011001100011 #
b10110001111100000101011001100011 '
b10110001111100000101011001100011 .
b10110001111100000101011001100011 4
b10110001111100000101011001100011 :
b10110001111100000101011001100011 @
b10110001111100000101011001100011 F
b10000100100001001101011000001001 $
b10000100100001001101011000001001 (
b10000100100001001101011000001001 /
b10000100100001001101011000001001 5
b10000100100001001101011000001001 ;
b10000100100001001101011000001001 A
b10000100100001001101011000001001 G
1%
#1500
0%
#2000
b1000000001001100001111010000000 I
b1000000011001101110001010000000 C
b10111001000000000000010001110010 =
b1001101100110010001010010011010 7
b1000110111111111111101110001101 1
b110100110010001100100001101 +
0&
0*
b1000110110111111001100110001101 #
b1000110110111111001100110001101 '
b1000110110111111001100110001101 .
b1000110110111111001100110001101 4
b1000110110111111001100110001101 :
b1000110110111111001100110001101 @
b1000110110111111001100110001101 F
b110101110010111101100001101 $
b110101110010111101100001101 (
b110101110010111101100001101 /
b110101110010111101100001101 5
b110101110010111101100001101 ;
b110101110010111101100001101 A
b110101110010111101100001101 G
1%
#2500
0%
#3000
1J
b11010110011101001100110110101101 I
1D
b111011111101011101011001110111 C
1>
b1000100000010000010100110001000 =
18
19
b0xx1xx "
b111011111110011101011001110111 7
12
b10111011111101111101011001110111 1
1,
1!
b10000000000000100000000000000000 +
1&
1*
b10001001001101110101001000010010 #
b10001001001101110101001000010010 '
b10001001001101110101001000010010 .
b10001001001101110101001000010010 4
b10001001001101110101001000010010 :
b10001001001101110101001000010010 @
b10001001001101110101001000010010 F
b10110010110000101000010001100101 $
b10110010110000101000010001100101 (
b10110010110000101000010001100101 /
b10110010110000101000010001100101 5
b10110010110000101000010001100101 ;
b10110010110000101000010001100101 A
b10110010110000101000010001100101 G
1%
#3500
0%
#4000
0J
b101111000111110101000001100 I
0D
b110001001000010111000001100 C
0>
b11111001000010000001000011110010 =
08
09
b0xx0xx "
b111110010111011000000001110 7
02
b110111101111110111100001101 1
0,
0!
b110100111100000100000001 +
0&
0*
b110110101111100110100001101 #
b110110101111100110100001101 '
b110110101111100110100001101 .
b110110101111100110100001101 4
b110110101111100110100001101 :
b110110101111100110100001101 @
b110110101111100110100001101 F
b111100111110001100000001 $
b111100111110001100000001 (
b111100111110001100000001 /
b111100111110001100000001 5
b111100111110001100000001 ;
b111100111110001100000001 A
b111100111110001100000001 G
1%
#4500
0%
#5000
1J
b11100011011010011101101111000111 I
1D
b100101101011100011110001001011 C
1>
b11000000010100000000001010000000 =
18
b1011001101100011011111010110011 7
12
b111111101011111111110101111111 1
1,
1!
b11010000000011100000100110100 +
1&
1*
b11110100011011100110100111101 #
b11110100011011100110100111101 '
b11110100011011100110100111101 .
b11110100011011100110100111101 4
b11110100011011100110100111101 :
b11110100011011100110100111101 @
b11110100011011100110100111101 F
b111011001000111111000101110110 $
b111011001000111111000101110110 (
b111011001000111111000101110110 /
b111011001000111111000101110110 5
b111011001000111111000101110110 ;
b111011001000111111000101110110 A
b111011001000111111000101110110 G
1%
#5500
0%
#6000
b11001111010110011001111110011111 I
b110000111110011010000001100001 C
b10001001000000100000100000010010 =
b10111101000000100100111101111001 7
b1110110111111011111011111101101 1
b1000110000001000101011110001100 +
0&
0*
b1000110001011011111011110001100 #
b1000110001011011111011110001100 '
b1000110001011011111011110001100 .
b1000110001011011111011110001100 4
b1000110001011011111011110001100 :
b1000110001011011111011110001100 @
b1000110001011011111011110001100 F
b1110110110101000101011111101101 $
b1110110110101000101011111101101 (
b1110110110101000101011111101101 /
b1110110110101000101011111101101 5
b1110110110101000101011111101101 ;
b1110110110101000101011111101101 A
b1110110110101000101011111101101 G
1%
#6500
0%
#7000
1K
b1xx0xx "
b1100110001110010011101011001101 I
b10011111110010101100110100111111 C
b1001000000000 =
b1100000001101010000111010111111 7
b11111111111111111110110111111111 1
b1100000001101010010000011000000 +
1&
1*
b11100011001101110010010011000110 #
b11100011001101110010010011000110 '
b11100011001101110010010011000110 .
b11100011001101110010010011000110 4
b11100011001101110010010011000110 :
b11100011001101110010010011000110 @
b11100011001101110010010011000110 F
b1111100111111011110100111111001 $
b1111100111111011110100111111001 (
b1111100111111011110100111111001 /
b1111100111111011110100111111001 5
b1111100111111011110100111111001 ;
b1111100111111011110100111111001 A
b1111100111111011110100111111001 G
1%
#7500
0%
#8000
0K
b11110010000111000100110111100101 I
b110111111001000101011001101111 C
b1000000010000010100100010000 =
19
b0xx1xx "
b10111000000010110101011101101111 7
b11110111111101111101011011101111 1
b11000000000100111000000010000000 +
0&
0*
b11010101000100111101001010101010 #
b11010101000100111101001010101010 '
b11010101000100111101001010101010 .
b11010101000100111101001010101010 4
b11010101000100111101001010101010 :
b11010101000100111101001010101010 @
b11010101000100111101001010101010 F
b11100010111101111000010011000101 $
b11100010111101111000010011000101 (
b11100010111101111000010011000101 /
b11100010111101111000010011000101 5
b11100010111101111000010011000101 ;
b11100010111101111000010011000101 A
b11100010111101111000010011000101 G
1%
#8500
0%
#9000
1K
b1001001001000100111101010010010 I
b11001001011111011000010110010010 C
b100000000000000100000001000 =
09
b1xx0xx "
b101110100000100110101001011100 7
b11111011111111111111011111110111 1
b110010100000100111001001100101 +
1&
1*
b10111011110100100111001001110111 #
b10111011110100100111001001110111 '
b10111011110100100111001001110111 .
b10111011110100100111001001110111 4
b10111011110100100111001001110111 :
b10111011110100100111001001110111 @
b10111011110100100111001001110111 F
b1110010101011111111011111100101 $
b1110010101011111111011111100101 (
b1110010101011111111011111100101 /
b1110010101011111111011111100101 5
b1110010101011111111011111100101 ;
b1110010101011111111011111100101 A
b1110010101011111111011111100101 G
1%
#9500
0%
#10000
b10111110101110100000010101111101 I
b11001110110111100000110110011101 C
b110000000000010010000001100000 =
b11010001000111111011000110100001 7
b11001111111111101101111110011111 1
b1001000001101001000000010 +
0&
0*
b1000111111011001101101110001111 #
b1000111111011001101101110001111 '
b1000111111011001101101110001111 .
b1000111111011001101101110001111 4
b1000111111011001101101110001111 :
b1000111111011001101101110001111 @
b1000111111011001101101110001111 F
b10001001001100101101011000010010 $
b10001001001100101101011000010010 (
b10001001001100101101011000010010 /
b10001001001100101101011000010010 5
b10001001001100101101011000010010 ;
b10001001001100101101011000010010 A
b10001001001100101101011000010010 G
1%
#10500
0%
#11000
b1101110010001100010110011011100 I
b10011110010001101111111100111100 C
b100010010000000000000001 =
b1100000101001110000000011000000 7
b11111111011101101111111111111110 1
b1100001001100000000000011000010 +
1&
1*
b11100111011101101001011011001110 #
b11100111011101101001011011001110 '
b11100111011101101001011011001110 .
b11100111011101101001011011001110 4
b11100111011101101001011011001110 :
b11100111011101101001011011001110 @
b11100111011101101001011011001110 F
b1111001001100000110100111110010 $
b1111001001100000110100111110010 (
b1111001001100000110100111110010 /
b1111001001100000110100111110010 5
b1111001001100000110100111110010 ;
b1111001001100000110100111110010 A
b1111001001100000110100111110010 G
1%
#11500
0%
#12000
0K
b11101110110010011101001111011101 I
b10110110010100011010000101101 C
b1001001101011000000100010010 =
19
b0xx1xx "
b11010110110010101100100110101101 7
b11110110110010100111111011101101 1
b11100000000000000100101011000000 +
0&
0*
b11100010110010100100111011000101 #
b11100010110010100100111011000101 '
b11100010110010100100111011000101 .
b11100010110010100100111011000101 4
b11100010110010100100111011000101 :
b11100010110010100100111011000101 @
b11100010110010100100111011000101 F
b11110100000000000111101011101000 $
b11110100000000000111101011101000 (
b11110100000000000111101011101000 /
b11110100000000000111101011101000 5
b11110100000000000111101011101000 ;
b11110100000000000111101011101000 A
b11110100000000000111101011101000 G
1%
#12500
0%
#13000
1K
b10110000001101011101111101100001 I
b11110000110101100110000111100001 C
b1001000011001011000000010 =
09
b1xx0xx "
b1100111001100111001000011001 7
b11111110110111100110100111111101 1
b1110000010000000100000011100 +
1&
1*
b11011110100011100010100010111101 #
b11011110100011100010100010111101 '
b11011110100011100010100010111101 .
b11011110100011100010100010111101 4
b11011110100011100010100010111101 :
b11011110100011100010100010111101 @
b11011110100011100010100010111101 F
b101110010110000100100101011100 $
b101110010110000100100101011100 (
b101110010110000100100101011100 /
b101110010110000100100101011100 5
b101110010110000100100101011100 ;
b101110010110000100100101011100 A
b101110010110000100100101011100 G
1%
#13500
0%
#14000
0J
0K
b11011111110111100111000111000 I
0D
b100100000011000111111001001000 C
0>
b1001001010100001000000110010010 =
08
19
b0xx1xx "
b1001001010100100111111010010010 7
02
b10110110101011110111111001101101 1
0,
0!
b10010010101000110000000000100101 +
0&
0*
b10110010101001110010011001100101 #
b10110010101001110010011001100101 '
b10110010101001110010011001100101 .
b10110010101001110010011001100101 4
b10110010101001110010011001100101 :
b10110010101001110010011001100101 @
b10110010101001110010011001100101 F
b10010110101010110101100000101101 $
b10010110101010110101100000101101 (
b10010110101010110101100000101101 /
b10010110101010110101100000101101 5
b10010110101010110101100000101101 ;
b10010110101010110101100000101101 A
b10010110101010110101100000101101 G
1%
#14500
0%
#15000
1K
b1010011100001000010010010100111 I
b10110100100111001110010101101001 C
b1001010000000000001100010010100 =
09
b1xx0xx "
b10110111011000101110100101101101 7
b10110101111111111110011101101011 1
b1011000110000001000000010 +
1&
1*
b101011100111000011100001010 #
b101011100111000011100001010 '
b101011100111000011100001010 .
b101011100111000011100001010 4
b101011100111000011100001010 :
b101011100111000011100001010 @
b101011100111000011100001010 F
b10110001111011110110001001100011 $
b10110001111011110110001001100011 (
b10110001111011110110001001100011 /
b10110001111011110110001001100011 5
b10110001111011110110001001100011 ;
b10110001111011110110001001100011 A
b10110001111011110110001001100011 G
1%
#15500
0%
#16000
1J
b1010000001010001111111010100000 I
1D
b11010000010111110000001110100000 C
1>
b101111100000001101110001011111 =
18
b11010000100111110100001110100000 7
12
b11010000011111110010001110100000 1
1,
1!
b1000000010000000000000 +
0&
0*
b10000011001000010000100100000 #
b10000011001000010000100100000 '
b10000011001000010000100100000 .
b10000011001000010000100100000 4
b10000011001000010000100100000 :
b10000011001000010000100100000 @
b10000011001000010000100100000 F
b11000000001110110010001010000000 $
b11000000001110110010001010000000 (
b11000000001110110010001010000000 /
b11000000001110110010001010000000 5
b11000000001110110010001010000000 ;
b11000000001110110010001010000000 A
b11000000001110110010001010000000 G
1%
#16500
0%
#17000
b1111001010101001000011011110011 I
b10011011101101001000100100110111 C
b100000000000110011001001000000 =
b100100010001010001001001000111 7
b11011111111111001100110110111111 1
b1000100010010000100010010001000 +
1&
1*
b11001110110011001100110010011101 #
b11001110110011001100110010011101 '
b11001110110011001100110010011101 .
b11001110110011001100110010011101 4
b11001110110011001100110010011101 :
b11001110110011001100110010011101 @
b11001110110011001100110010011101 F
b1010101011110000100010110101010 $
b1010101011110000100010110101010 (
b1010101011110000100010110101010 /
b1010101011110000100010110101010 5
b1010101011110000100010110101010 ;
b1010101011110000100010110101010 A
b1010101011110000100010110101010 G
1%
#17500
0%
#18000
0K
b10111110011000110111100101111101 I
b1000010101000111000011010000101 C
b110100010111000100000101101000 =
19
b0xx1xx "
b1010100101000111111011010101001 7
b11001011101000111011111010010111 1
b10001001000000000011100000010010 +
0&
0*
b10001001100000111011100000010011 #
b10001001100000111011100000010011 '
b10001001100000111011100000010011 .
b10001001100000111011100000010011 4
b10001001100000111011100000010011 :
b10001001100000111011100000010011 @
b10001001100000111011100000010011 F
b11001011001000000011111010010110 $
b11001011001000000011111010010110 (
b11001011001000000011111010010110 /
b11001011001000000011111010010110 5
b11001011001000000011111010010110 ;
b11001011001000000011111010010110 A
b11001011001000000011111010010110 G
1%
#18500
0%
#19000
0J
b100010111010111001111001000110 I
0D
b101111000110111110111001011110 C
0>
b1010000010000000000000110100000 =
08
b110000011001000000111001100000 7
02
b10101111101111111111111001011111 1
0,
0!
b10000000101001000001000000000001 +
1&
1*
b10101001101001111101011001010011 #
b10101001101001111101011001010011 '
b10101001101001111101011001010011 .
b10101001101001111101011001010011 4
b10101001101001111101011001010011 :
b10101001101001111101011001010011 @
b10101001101001111101011001010011 F
b10000110101111000011100000001101 $
b10000110101111000011100000001101 (
b10000110101111000011100000001101 /
b10000110101111000011100000001101 5
b10000110101111000011100000001101 ;
b10000110101111000011100000001101 A
b10000110101111000011100000001101 G
1%
